[
  { "token": "ржЯрзНрж░рж╛ржиржЬрзЗржирзНржбрж╛рж░", "replace": [] },
  { "token": "ржЗржЬрж░рж╛рзЯрзЗрж▓", "replace": [] },
  { "token": "рж╣рж╛ржорж╛рж╕", "replace": [] },
  { "token": "ржЬрж┐рж╣рж╛ржж", "replace": [] },
  { "token": "ржПрж▓ржЬрж┐ржмрж┐ржЯрж┐ржХрж┐ржЙ", "replace": [] },
  { "token": "ржХрж╛ржлрж┐рж░", "replace": [] },
  { "token": "ржорзБрж╢рж░рж┐ржХ", "replace": [] },
  { "token": "ржЯрзНрж░рж╛ржирзНрж╕ржЬрзЗржирзНржбрж╛рж░", "replace": [] },
  { "token": "ржЗрзЯрзЗржорзЗржирж┐", "replace": [] },
  { "token": "рж╢рж╛ржЗржЦ", "replace": [] },
  { "token": "рзп/рззрзз", "replace": [] },
  { "token": "ржЫрж╛рждрзНрж░ржжрзЗрж░ ржжрж▓", "replace": [] },
  {
    "token": "ржХрзНрж░рзБрж╕рзЗржб",
    "replace": []
  },
  { "token": "ржХрзБрж░ржмрж╛ржирзА", "replace": [] },
  { "token": "ржХрж┐рждрж╛рж▓", "replace": [] },
  { "token": "ржХрж┐рж╕рж╛рж╕", "replace": [] },
  { "token": "ржХрзБржлрж░рзА", "replace": [] },
  { "token": "ржХрж╛ржлрж┐рж░", "replace": [] },
  { "token": "ржЖржлржЧрж╛ржи", "replace": [] },
  { "token": "ржЖржХрж╕рж╛", "replace": [] },
  { "token": "ржЖржорзЗрж░рж┐ржХрж╛", "replace": [] },
  { "token": "ржЗрж╕рж░рж╛ржЗрж▓", "replace": [] },
  { "token": "ржЗрзЯрж╛рж╣рзБржжрж┐", "replace": [] },
  { "token": "ржЬрж╛рзЯрж╛ржирж┐рж╖рзНржЯ", "replace": [] },
  { "token": "ржпрзБржжрзНржз", "replace": [] },
  { "token": "рж╣рждрзНржпрж╛", "replace": [] },
  { "token": "ржЦрзБржи", "replace": [] },
  { "token": "ржЬрж┐рж╣рж╛ржж", "replace": [] },
  { "token": "рж╢рж╛рж╕рзНрждрж┐", "replace": [] },
  { "token": "ржЦрж┐рж▓рж╛ржлрж╛рж╣", "replace": [] },
  { "token": "рждрж╛рж▓рж┐ржмрж╛ржи", "replace": [] },
  { "token": "ржорзБржЬрж╛рж╣рж┐ржж ", "replace": [] },
  { "token": "ржЬржЩрзНржЧрзА", "replace": [] },
  { "token": "ржорзБрж░рждрж╛ржж", "replace": [] },
  { "token": "ржорзБржирж╛ржлрж┐ржХ", "replace": [] },
  { "token": "рж╢рж╛рж╕ржХ", "replace": [] },
  { "token": "ржЯрзНрж░рж╛ржирзНрж╕ржЬрзЗржирзНржбрж╛рж░", "replace": [] },
  { "token": "рждрж╛ржХржлрж┐рж░", "replace": [] },
  { "token": "ржорж╛рж╣ржжрж┐", "replace": [] },
  { "token": "ржжрж╛ржЬрзНржЬрж╛рж▓", "replace": [] },
  { "token": "рж╢рж╛ржо", "replace": [] },
  { "token": "рж╢рж╛рждрж┐ржо ржЗрждрзНржпрж╛ржжрж┐ред", "replace": [] },
  { "token": "israel", "replace": ["ЁРМЙЁРМФ╔╜ЁРМАЁРМДЁРМЛ", "ъТРъЗЩъЛкъЛмъПВъТТ", "ъАдъМЧъЛкъНПъНЯъТТ"] }
]
